ESpvt/ESResolutionScanner.py
ESpvt/__init__.py
espvt-1.0.4.dist-info/licenses/LICENSE
espvt-1.0.4.dist-info/METADATA
espvt-1.0.4.dist-info/WHEEL
espvt-1.0.4.dist-info/top_level.txt
espvt-1.0.4.dist-info/RECORD
